tgcrypto_optimized/__init__.py
tgcrypto_optimized/tgcrypto_optimized.cpython-311-x86_64-linux-musl.so
tgcrypto_optimized-0.3.4.dist-info/METADATA
tgcrypto_optimized-0.3.4.dist-info/WHEEL
tgcrypto_optimized-0.3.4.dist-info/top_level.txt
tgcrypto_optimized-0.3.4.dist-info/RECORD
