Metadata-Version: 2.2
Name: tgcrypto-optimized
Version: 0.3.4
Summary: Cryptographic utilities for Telegram.
Author: Telectron inc.
License: CC0
Keywords: telegram crypto cryptography mtproto aes
Classifier: Development Status :: 4 - Beta
Classifier: Intended Audience :: Developers
Classifier: Topic :: Security :: Cryptography
Classifier: License :: CC0 1.0 Universal (CC0 1.0) Public Domain Dedication
Classifier: Programming Language :: Python :: 3
Classifier: Programming Language :: Python :: 3.6
Classifier: Programming Language :: Python :: 3.7
Classifier: Programming Language :: Python :: 3.8
Classifier: Programming Language :: Python :: 3.9
Classifier: Programming Language :: Python :: 3.10
Requires-Python: >=3.3
Dynamic: author
Dynamic: classifier
Dynamic: description-content-type
Dynamic: keywords
Dynamic: license
Dynamic: requires-python
Dynamic: summary
